atlantiscore/__init__.py
atlantiscore/db/__init__.py
atlantiscore/db/types/__init__.py
atlantiscore/db/types/evm/__init__.py
atlantiscore/db/types/evm/address.py
atlantiscore/db/types/evm/base.py
atlantiscore/db/types/evm/transaction.py
atlantiscore/hash/__init__.py
atlantiscore/hash/ecdsa.py
atlantiscore/lib/__init__.py
atlantiscore/lib/eth.py
atlantiscore/lib/exceptions.py
atlantiscore/lib/string.py
atlantiscore/lib/abi/__init__.py
atlantiscore/lib/abi/erc20.abi
atlantiscore/middleware/__init__.py
atlantiscore/middleware/blockchain/__init__.py
atlantiscore/middleware/blockchain/erc20.py
atlantiscore/middleware/blockchain/evm.py
atlantiscore/types/__init__.py
atlantiscore/types/key.py
atlantiscore/types/evm/__init__.py
atlantiscore/types/evm/address.py
atlantiscore/types/evm/base.py
atlantiscore/types/evm/transaction.py
atlantiscore-12.1.1.dist-info/METADATA
atlantiscore-12.1.1.dist-info/WHEEL
atlantiscore-12.1.1.dist-info/top_level.txt
atlantiscore-12.1.1.dist-info/RECORD
