Metadata-Version: 2.4
Name: atlantiscore
Version: 12.1.1
Summary: atlantiscore
Author-email: Atlantis Labs <r00tail@protonmail.com>
Requires-Dist: aiofiles~=23.2
Requires-Dist: codercore~=8.1.3
Requires-Dist: coincurve~=20.0
Requires-Dist: eth-hash[pycryptodome]~=0.5
Requires-Dist: eth-utils~=4.1
Requires-Dist: pydantic~=2.5
Requires-Dist: sqlalchemy[asyncio]~=2.0
Requires-Dist: web3[ipfs]~=6.9
Provides-Extra: test
Requires-Dist: pytest~=7.2.0; extra == "test"
Requires-Dist: pytest-asyncio~=0.20.1; extra == "test"
Requires-Dist: pytest-cov~=4.0.0; extra == "test"
Requires-Dist: pytest-mock~=3.10.0; extra == "test"
Requires-Dist: pytest-xdist[psutil]~=3.0.2; extra == "test"
Provides-Extra: dev
Requires-Dist: alembic~=1.13; extra == "dev"
Requires-Dist: black~=22.12; extra == "dev"
Requires-Dist: bumpver~=2022.1120; extra == "dev"
Requires-Dist: flake8~=6.0; extra == "dev"
Requires-Dist: isort~=5.12; extra == "dev"
Requires-Dist: pre-commit~=2.21; extra == "dev"
